cyberonix/__init__.py
cyberonix/cyberonix.py
cyberonix/main/Bug_Bounty.py
cyberonix/main/__init__.py
cyberonix/main/arguments.py
cyberonix/main/tool.py
cyberonix/main/tools/Anonymity.py
cyberonix/main/tools/Authentication.py
cyberonix/main/tools/Authorization.py
cyberonix/main/tools/Configuration_Management.py
cyberonix/main/tools/Cryptography.py
cyberonix/main/tools/Exploitation_Tools.py
cyberonix/main/tools/File_Upload.py
cyberonix/main/tools/Framework.py
cyberonix/main/tools/Password_Hacking.py
cyberonix/main/tools/Pentesting_Bug_Bounty.py
cyberonix/main/tools/PostExploitationAttacks.py
cyberonix/main/tools/Recommended_Tool.py
cyberonix/main/tools/RiskyFuncPayment.py
cyberonix/main/tools/Secure_Transmission.py
cyberonix/main/tools/Session_Management.py
cyberonix/main/tools/Sniffing_and_Spoofing.py
cyberonix/main/tools/Vulnerability_Analysis.py
cyberonix/main/tools/WEB_Application_Analysis.py
cyberonix/main/tools/Wireless_Hacking.py
cyberonix/main/tools/__init__.py
cyberonix/main/tools/banner.py
cyberonix/main/tools/colors.py
cyberonix/main/tools/data_validation.py
cyberonix/main/tools/dos.py
cyberonix/main/tools/forensic.py
cyberonix/main/tools/html5.py
cyberonix/main/tools/information_gathering.py
cyberonix/main/tools/run_on_browser.py
cyberonix/main/tools/template.py
cyberonix/main/tools/waiting.py
cyberonix/main/tools/writeup.py
cyberonix-3.0.6.dist-info/METADATA
cyberonix-3.0.6.dist-info/WHEEL
cyberonix-3.0.6.dist-info/entry_points.txt
cyberonix-3.0.6.dist-info/top_level.txt
cyberonix-3.0.6.dist-info/RECORD
