Metadata-Version: 2.1
Name: cyberonix
Version: 3.0.6
Summary: Cyberonix is a complete resource hub for Cyber Security Community.
Home-page: https://github.com/TeamDefronix/Cyberonix
Author: Defronix
Author-email: hello@defronix.com
License: MIT
Classifier: Development Status :: 5 - Production/Stable
Classifier: Intended Audience :: Developers
Classifier: License :: OSI Approved :: MIT License
Classifier: Operating System :: OS Independent
Classifier: Programming Language :: Python :: 3
Classifier: Programming Language :: Python :: 3.6
Classifier: Programming Language :: Python :: 3.7
Classifier: Programming Language :: Python :: 3.8
Classifier: Programming Language :: Python :: 3.9
Classifier: Programming Language :: Python :: 3.10
Classifier: Topic :: Security
Requires-Dist: beautifulsoup4
Requires-Dist: requests
Requires-Dist: ipwhois
Requires-Dist: dnspython
Requires-Dist: selenium (==4.7.2)
Requires-Dist: netifaces
